yukawa/__init__.py
yukawa/yukawa.py
yukawa-0.0.2.dist-info/LICENSE
yukawa-0.0.2.dist-info/METADATA
yukawa-0.0.2.dist-info/WHEEL
yukawa-0.0.2.dist-info/top_level.txt
yukawa-0.0.2.dist-info/RECORD
