Metadata-Version: 2.1
Name: yukawa
Version: 0.0.2
Summary: Get massive fermions from a given scalar Abelian charge
Home-page: https://github.com/restrepo/yukawa
Author: restrepo
Author-email: restrepo@udea.edu.co
License: BSD
License-File: LICENSE
